[{"name":"Bob Dylan","category":"Musician/band","id":"11955325695","created_time":"2012-03-25T05:20:47+0000"},{"name":"The Miracles","category":"Musician/band","id":"105980922766553","created_time":"2012-03-25T05:20:46+0000"},{"name":"Queen","category":"Musician/band","id":"17337462361","created_time":"2012-01-23T17:02:45+0000"},{"name":"Prince","category":"Musician/band","id":"103754739663042","created_time":"2012-01-23T17:02:44+0000"},{"name":"Led Zeppelin Official","category":"Musician/band","id":"131572223581891","created_time":"2012-01-23T17:02:42+0000"},{"name":"Guns N' Roses","category":"Musician/band","id":"10901008068","created_time":"2012-01-23T17:02:42+0000"},{"name":"Coldplay","category":"Musician/band","id":"15253175252","created_time":"2011-10-17T07:36:30+0000"},{"name":"Harsha Iyer","category":"Musician/band","id":"267420853284035","created_time":"2011-09-30T11:40:17+0000"},{"name":"Poets of the Fall","category":"Musician/band","id":"7555982895","created_time":"2011-08-07T06:42:43+0000"},{"name":"Parodesy Noise","category":"Musician/band","id":"161444830568628","created_time":"2011-04-10T08:09:25+0000"},{"name":"George Harrison","category":"Musician/band","id":"20929721344","created_time":"2011-03-27T15:58:29+0000"},{"name":"Good Girl Gone Bad","category":"Album","id":"105497966151560","created_time":"2011-01-12T16:33:31+0000"},{"name":"21 guns - Green Day","category":"Musician/band","id":"112457915771","created_time":"2010-12-09T17:53:58+0000"},{"name":"Vampire Weekend","category":"Musician/band","id":"103106703062915","created_time":"2010-12-09T05:13:48+0000"},{"name":"Green Day","category":"Musician/band","id":"21275344520","created_time":"2010-12-09T05:13:48+0000"},{"name":"ABBA","category":"Musician/band","id":"124611394231248","created_time":"2010-07-01T01:38:18+0000"},{"name":"Metallica","category":"Musician/band","id":"10212595263","created_time":"2010-06-22T16:32:15+0000"},{"name":"The Beatles","category":"Musician/band","id":"69116329538","created_time":"2010-06-06T14:52:38+0000"},{"name":"ELVIS PRESLEY","category":"Musician/band","id":"7284978791","created_time":"2010-06-06T14:52:38+0000"},{"name":"R.E.M.","category":"Musician/band","id":"8759772983","created_time":"2010-05-04T04:31:55+0000"},{"name":"Karthik","category":"Musician/band","id":"103754796330123","created_time":"2010-04-30T06:26:31+0000"},{"name":"Shreya Goshal","category":"Musician/band","id":"108091805891854","created_time":"2010-04-30T06:26:31+0000"},{"name":"Savage Garden","category":"Musician/band","id":"20251714228","created_time":"2010-04-30T06:26:30+0000"},{"name":"Michael Jackson","category":"Musician/band","id":"19691681472","created_time":"2010-04-30T06:26:30+0000"},{"name":"Natasha Bedingfield","category":"Musician/band","id":"7373504254","created_time":"2010-04-30T06:26:30+0000"},{"name":"James Blunt","category":"Musician/band","id":"16855985423","created_time":"2010-04-30T06:26:30+0000"},{"name":"Linkin Park","category":"Musician/band","id":"8210451787","created_time":"2010-04-30T06:26:30+0000"},{"name":"Nancy Sinatra","category":"Musician/band","id":"108011975894413","created_time":"2010-04-30T06:26:30+0000"},{"name":"Bill Withers","category":"Musician/band","id":"59637263183","created_time":"2010-04-30T06:26:30+0000"},{"name":"George Michael","category":"Musician/band","id":"11546961094","created_time":"2010-04-30T06:26:29+0000"},{"name":"Bobby McFerrin","category":"Musician/band","id":"105475352820769","created_time":"2010-04-30T06:26:29+0000"},{"name":"A.R. Rahman","category":"Musician/band","id":"63441126719","created_time":"2010-01-07T13:14:49+0000"},{"name":"Karthik (Singer)","category":"Community","id":"74780941496","created_time":"2009-11-04T16:43:42+0000"},{"name":"A.R.Rahman","category":"Musician/band","id":"19242824063","created_time":"2009-07-21T01:39:56+0000"}]